dbxfs/__init__.py
dbxfs/cachingfs.py
dbxfs/dbxfs.py
dbxfs/disable_quick_look.py
dbxfs/gui.py
dbxfs/macos_proxies_crash_fix.py
dbxfs/main.py
dbxfs/py.typed
dbxfs/safefs_glue.py
dbxfs/translate_ignored_files.py
dbxfs/util_dumpster.py
dbxfs/version.py
dbxfs-2.0.1.dist-info/LICENSE
dbxfs-2.0.1.dist-info/METADATA
dbxfs-2.0.1.dist-info/WHEEL
dbxfs-2.0.1.dist-info/entry_points.txt
dbxfs-2.0.1.dist-info/top_level.txt
dbxfs-2.0.1.dist-info/RECORD
