Metadata-Version: 2.1
Name: dbxfs
Version: 2.0.1
Summary: User-space file system for Dropbox
Home-page: https://thelig.ht/code/dbxfs
Author: Rian Hunter
Author-email: rian@alum.mit.edu
License: GPL3
Classifier: Development Status :: 5 - Production/Stable
Classifier: Programming Language :: Python :: 3
Classifier: Topic :: System :: Filesystems
Requires-Python: >=3.11
License-File: LICENSE
Requires-Dist: block-tracing (<2,>=1.0.1)
Requires-Dist: dropbox (>=11.25.0)
Requires-Dist: platformdirs (<5,>=4.1.0)
Requires-Dist: privy (<7,>=6.0)
Requires-Dist: sentry-sdk (<2,>=1.39)
Requires-Dist: userspacefs (<4,>=3.1.0)
Requires-Dist: pywin32 ; sys_platform == "win32"
Provides-Extra: safefs
Requires-Dist: safefs ; extra == 'safefs'
